lab2/memory/datamem_ans.v
`timescale 1ns/1ps
`define MEM_DEPTH  1024
`define MEM_WIDTH  8
`define WORD_WIDTH 32
module datamem_ans(
  );

  reg [`MEM_WIDTH-1:0] memory [0:`MEM_DEPTH-1];

  initial begin
    $readmemh("datamem_ans_parse.txt",memory);
  end
endmodule

lab2_mod2/datamem.v
`timescale 1ns/1ps
`define MEM_DEPTH  1024
`define MEM_WIDTH  8
`define WORD_WIDTH 32
module datamem(
  clk,
  data_addr,
  data_wr,
  data_in, //input to processor
  data_out //output of processor
  );
  input clk,data_wr;
  input [`WORD_WIDTH-1:0] data_addr,data_out;
  output [`WORD_WIDTH-1:0] data_in;

  reg [`MEM_WIDTH-1:0] memory [0:`MEM_DEPTH-1];

  initial begin
    $readmemh("datamem_parse.txt",memory);
  end

  //Read port
  reg [`WORD_WIDTH-1:0] data_in;

  always@(*)
    data_in <= {memory[data_addr],
                memory[data_addr+1],
                memory[data_addr+2],
                memory[data_addr+3]};

  //Write port
  always@(posedge clk)
    if (data_wr) begin
      memory[data_addr] <= data_out[31:24];
      memory[data_addr+1] <= data_out[23:16];
      memory[data_addr+2] <= data_out[15:8];
      memory[data_addr+3] <= data_out[7:0];
    end
endmodule

lab2_mod/memory/instmem.v
`timescale 1ns/1ps
`define MEM_DEPTH  1024
`define MEM_WIDTH  8
`define WORD_WIDTH 32
module instmem(
  inst_addr,
  inst
  );
  input [`WORD_WIDTH-1:0] inst_addr;
  output [`WORD_WIDTH-1:0] inst;

  reg [`MEM_WIDTH-1:0] memory [0:`MEM_DEPTH-1];

  initial begin
    $readmemh("instmem_parse.txt",memory);
  end

  //Read port
  reg [`WORD_WIDTH-1:0] inst;

  always@(*)
    inst <= {memory[inst_addr],
             memory[inst_addr+1],
             memory[inst_addr+2],
             memory[inst_addr+3]};

endmodule

checker/rtl/alu.v
`timescale 1ns/1ps
`define WORD_WIDTH 32

module alu ( opA, opB, sel, res, z, neg );
	input [`WORD_WIDTH-1:0] opA;
	input [`WORD_WIDTH-1:0]	opB;
	input [1:0] sel;	
	output reg [31:0] res;
	output z;
	output neg;

	wire [`WORD_WIDTH-1:0] res_add;
	wire [`WORD_WIDTH-1:0] res_sub;
	wire cout;

	assign {cout, res_add} = {1'b0, opA} + {1'b0, opB};
	assign {cout, res_sub} = {1'b0, opA} + {1'b0, ~opB} + 1'b1;

	/* res output */
	always @ (*)
		case (sel)
			2'd0: res <= res_add;
			2'd1: res <= res_sub;			
		endcase

	/* zero flag */
	assign z = (res == 0) ? 1'b1 : 1'b0;

	/* negative number flag */
	assign neg = ((cout == 1'b1) && (res_sub[31] == 1'b1)) ? 1'b1 : 1'b0;

endmodule

lab3/rtl/rf.v
`timescale 1ns/1ps
`define MEM_DEPTH  32
`define MEM_WIDTH  32
`define WORD_WIDTH 32

module rf(
	input clk,
	input rst_n,
	input [4:0] rd_addrA,
	input [4:0] rd_addrB,
	output [`WORD_WIDTH-1:0] rd_dataA,
	output [`WORD_WIDTH-1:0] rd_dataB,
	input wr_en,
	input [4:0] wr_addr,
	input [`WORD_WIDTH-1:0] wr_data
);

	reg [`MEM_WIDTH-1:0] regf [`MEM_DEPTH-1:0];
	
	wire [31:0] reg1;
	wire [31:0] reg2;
	wire [31:0] reg3;
	wire [31:0] reg4;
	wire [31:0] reg5;
	wire [31:0] reg6;
	wire [31:0] reg7;
	wire [31:0] reg8;
	wire [31:0] reg9;
	wire [31:0] reg10;
	wire [31:0] reg11;
	wire [31:0] reg12;
	wire [31:0] reg13;
	wire [31:0] reg14;
	wire [31:0] reg15;
	wire [31:0] reg16;
	wire [31:0] reg17;
	wire [31:0] reg18;
	wire [31:0] reg19;
	wire [31:0] reg20;
	wire [31:0] reg21;
	wire [31:0] reg22;
	wire [31:0] reg23;
	wire [31:0] reg24;
	wire [31:0] reg25;
	wire [31:0] reg26;
	wire [31:0] reg27;
	wire [31:0] reg28;
	wire [31:0] reg29;
	wire [31:0] reg30;
	wire [31:0] reg31;
	wire [31:0] reg32;

	assign reg1 = regf[0];
	assign reg2 = regf[1];
	assign reg3 = regf[2];
	assign reg4 = regf[3];
	assign reg5 = regf[4];
	assign reg6 = regf[5];
	assign reg7 = regf[6];
	assign reg8 = regf[7];
	assign reg9 = regf[8];
	assign reg10 = regf[9];
	assign reg11 = regf[10];
	assign reg12 = regf[11];
	assign reg13 = regf[12];
	assign reg14 = regf[13];
	assign reg15 = regf[14];
	assign reg16 = regf[15];
	assign reg17 = regf[16];
	assign reg18 = regf[17];
	assign reg19 = regf[18];
	assign reg20 = regf[19];
	assign reg21 = regf[20];
	assign reg22 = regf[21];
	assign reg23 = regf[22];
	assign reg24 = regf[23];
	assign reg25 = regf[24];
	assign reg26 = regf[25];
	assign reg27 = regf[26];
	assign reg28 = regf[27];
	assign reg29 = regf[28];
	assign reg30 = regf[29];
	assign reg31 = regf[30];
	assign reg32 = regf[31];


	always @ (posedge clk, negedge rst_n)
		if (!rst_n) begin
			regf[0] <= 32'd0;
			regf[1] <= 32'd0;
			regf[2] <= 32'd0;
			regf[3] <= 32'd0;
			regf[4] <= 32'd0;
			regf[5] <= 32'd0;
			regf[6] <= 32'd0;
			regf[7] <= 32'd0;
			regf[8] <= 32'd0;
			regf[9] <= 32'd0;
			regf[10] <= 32'd0;
			regf[11] <= 32'd0;
			regf[12] <= 32'd0;
			regf[13] <= 32'd0;
			regf[14] <= 32'd0;
			regf[15] <= 32'd0;
			regf[16] <= 32'd0;
			regf[17] <= 32'd0;
			regf[18] <= 32'd0;
			regf[19] <= 32'd0;
			regf[20] <= 32'd0;
			regf[21] <= 32'd0;
			regf[22] <= 32'd0;
			regf[23] <= 32'd0;
			regf[24] <= 32'd0;
			regf[25] <= 32'd0;
			regf[26] <= 32'd0;
			regf[27] <= 32'd0;
			regf[28] <= 32'd0;
			regf[29] <= 32'd0;
			regf[30] <= 32'd0;
			regf[31] <= 32'd0;
		end
		else
			if (wr_en)
				case (wr_addr)
					5'd0: regf[wr_addr] <= 0;
					default: regf[wr_addr] <= wr_data;
				endcase

	assign rd_dataA = regf[rd_addrA];
	assign rd_dataB = regf[rd_addrB];

endmodule

lab3/rtl/single_cycle_mips.v
module single_cycle_mips ( clk, rst_n, inst_addr, inst, data_addr, data_in,
        data_out, data_wr );
  output [31:0] inst_addr;
  input [31:0] inst;
  output [31:0] data_addr;
  input [31:0] data_in;
  output [31:0] data_out;
  input clk, rst_n;
  output reg data_wr;

  parameter instBEQ = 6'b000100;
  parameter instBNE = 6'b000101;
  parameter instADDI = 6'b001000;
  parameter instSLTI = 6'b001010;
  parameter instSW = 6'b101011;
  parameter instLW = 6'b100011;

  parameter instRType = 6'd0;

  parameter functADD = 6'b100000;
  parameter functSUB = 6'b100010;
  parameter functSLT = 6'b101010;

	reg [4:0] rd_addrA;
	reg [4:0] rd_addrB;
	wire [31:0] rd_dataA;
	wire [31:0] rd_dataB;
	reg wr_en;
	reg [4:0] wr_addr;
	reg [31:0] wr_data;
	reg [5:0] opcode;
	reg [5:0] funct;

	/* Register File */
	rf R1 (.clk(clk),
		.rst_n(rst_n),
		.rd_addrA(rd_addrA),
		.rd_addrB(rd_addrB),
		.rd_dataA(rd_dataA),
		.rd_dataB(rd_dataB),
		.wr_en(wr_en),
		.wr_addr(wr_addr),
		.wr_data(wr_data)
	);

	/* Program Counter */
	reg [31:0] inst_addr;

	reg [`WORD_WIDTH-1:0] aluOpB;
	reg [1:0] aluSel;
	wire [`WORD_WIDTH-1:0] aluRes;
	wire aluZ;
	wire aluNeg;

	/* ALU */
	alu A1 (.opA(rd_dataA),
		.opB(aluOpB),
		.sel(aluSel),
		.res(aluRes),
		.z(aluZ),
		.neg(aluNeg)
	);

  always @ (*)
    rd_addrA <= inst[25:21];

  always @ (*)
    rd_addrB <= inst[20:16];

  always @ (*)
    opcode <= inst[31:26];

  always @ (*)
    funct <= inst[5:0];

	always @ (posedge clk, negedge rst_n)
		if (!rst_n)
			inst_addr <= 0;
		else
      case (opcode)
        instBEQ:
          if (aluZ)
            inst_addr <= (inst_addr + 4) + { {15{inst[15]}}, inst[15:0], 2'b0 };
          else
            inst_addr <= inst_addr + 4;
        instBNE:
          if (!aluZ)
            inst_addr <= (inst_addr + 4) + { {15{inst[15]}}, inst[15:0], 2'b0 };
          else
            inst_addr <= inst_addr + 4;
        default:
            inst_addr <= inst_addr + 4;
      endcase

	/* wr_addr input multiplexer for the reg file */
	always @ (*)
		case (opcode)
      instRType:
				wr_addr <= inst[15:11];		// rd
      instADDI,
      instSLTI,
      instSW,
      instLW:
				wr_addr <= inst[20:16];		// rt
			default:
				wr_addr <= inst[15:11];
		endcase

	/* wr_en control signal for reg file */
	always @ (*)
		case (opcode)
      instRType,
      instADDI,
      instSLTI,
      instLW:
				wr_en <= 1'b1;
			default:
				wr_en <= 1'b0;
		endcase

	/* aluOpB input multiplexer for the ALU */
	always @ (*)
		case (opcode)
      instRType:
				aluOpB <= rd_dataB;
      instADDI,
      instSLTI,
      instSW,
      instLW:
				aluOpB <= { {16{inst[15]}}, inst[15:0] };		// sign extend
			default:
				aluOpB <= rd_dataB;
		endcase

	parameter aluAdd = 2'd0;
	parameter aluSub = 2'd1;

	/* aluSel control signal for ALU */
	always @ (*)
		case (opcode)
      instRType:
				case (funct)
          functADD:
						aluSel <= aluAdd;
          functSUB,
          functSLT:
						aluSel <= aluSub;
					//default:
						//aluSel <= ???
				endcase
      instADDI,
      instSW,
      instLW:
				aluSel <= aluAdd;
      instBEQ,
      instBNE,
      instSLTI:
				aluSel <= aluSub;
		endcase

	/* data_wr control signal for the data memory */
	always @ (*)
		case (opcode)
      instSW:
				data_wr <= 1'b1;
			default:
				data_wr <= 1'b0;
		endcase

	/* wr_data input control signal for the reg file */
	always @ (*)
		case (opcode)
      instRType:
				case (funct)
          functSLT:
						wr_data <= 32'd1;
					default:
						wr_data <= aluRes;
				endcase
      instADDI:
				wr_data <= aluRes;
      instSLTI:
				wr_data <= 32'd1;
      instLW:
				wr_data <= data_in;
		endcase


	assign data_out = rd_dataB;
	assign data_addr = aluRes;
endmodule

lab3/sim/tb_single_cycle_mips.v
`timescale 1ns/1ps
`define CLK_PD 50
`define DEL_IN 3

module tb_single_cycle_mips();
	reg clk, rst_n;
	wire [31:0] inst_addr;
  wire [31:0] inst;
  wire [31:0] data_addr;
  wire [31:0] data_in;
  wire [31:0] data_out;
  wire data_wr;

	single_cycle_mips UUT ( .clk(clk),
		.rst_n(rst_n),
		.inst_addr(inst_addr),
		.inst(inst),
		.data_addr(data_addr),
		.data_in(data_in),
    .data_out(data_out),
		.data_wr(data_wr)
	);

	instmem I1 (.inst_addr(inst_addr),
		.inst(inst)
	);

	datamem D1 (.clk(clk),
  	.data_addr(data_addr),
  	.data_wr(data_wr),
  	.data_in(data_in),
  	.data_out(data_out)
	);

	datamem_ans D2();

	always #(`CLK_PD/2.0) clk = ~clk;

	integer i = 0;
	integer j = 0;
	integer k = 0;

	integer sw_w = 0;
	integer add_w = 0;
	integer sub_w = 0;
	integer slt_w = 0;
	integer addi_w = 0;
	integer slti_w = 0;
	integer beq_w = 0;
	integer bne_w = 0;

	initial begin
		$dumpfile("tb_proc.vcd");
		$dumpvars;
		// $vcdplusfile("tb_proc.vpd");
		// $vcdpluson;
		// $sdf_annotate("single_cycle_mips_mapped.sdf", UUT);

		clk = 0;
		rst_n = 0;

		#(`CLK_PD/2.0);
		#(`DEL_IN);
		rst_n = 1;

		$display("testbench starting...");

		while (k != 10) begin
			if (UUT.inst == 32'd0) begin
				k = k + 1;
			end
			#(`CLK_PD);
		end

		$display("\nPrinting the final contents of the data memory...");

		$display("data # \t\taddress \tdata	\tcorrect data");
		$display("-------- \t-------- \t-------- \t--------");
		while(j != 10) begin
			if ((i < 3) && (!beq_w)) begin
				if (
					(D1.memory[(i*4)] != D2.memory[(i*4)]) ||
					(D1.memory[(i*4)+1] != D2.memory[(i*4)+1]) ||
					(D1.memory[(i*4)+2] != D2.memory[(i*4)+2]) ||
					(D1.memory[(i*4)+3] != D2.memory[(i*4)+3])
					) begin
					beq_w = 1;
				end
			end

			if ((i > 3) && (i < 6) && (!bne_w)) begin
				if (
					(D1.memory[(i*4)] != D2.memory[(i*4)]) ||
					(D1.memory[(i*4)+1] != D2.memory[(i*4)+1]) ||
					(D1.memory[(i*4)+2] != D2.memory[(i*4)+2]) ||
					(D1.memory[(i*4)+3] != D2.memory[(i*4)+3])
					) begin
					bne_w = 1;
				end
			end

			if (i == 6) begin
				if (
					(D1.memory[(i*4)] != D2.memory[(i*4)]) ||
					(D1.memory[(i*4)+1] != D2.memory[(i*4)+1]) ||
					(D1.memory[(i*4)+2] != D2.memory[(i*4)+2]) ||
					(D1.memory[(i*4)+3] != D2.memory[(i*4)+3])
					) begin
					add_w = 1;
				end
			end

			if (i == 7) begin
				if (
					(D1.memory[(i*4)] != D2.memory[(i*4)]) ||
					(D1.memory[(i*4)+1] != D2.memory[(i*4)+1]) ||
					(D1.memory[(i*4)+2] != D2.memory[(i*4)+2]) ||
					(D1.memory[(i*4)+3] != D2.memory[(i*4)+3])
					) begin
					sub_w = 1;
				end
			end

			if (i == 8) begin
				if (
					(D1.memory[(i*4)] != D2.memory[(i*4)]) ||
					(D1.memory[(i*4)+1] != D2.memory[(i*4)+1]) ||
					(D1.memory[(i*4)+2] != D2.memory[(i*4)+2]) ||
					(D1.memory[(i*4)+3] != D2.memory[(i*4)+3])
					) begin
					slt_w = 1;
				end
			end

			if (i == 9) begin
				if (
					(D1.memory[(i*4)] != D2.memory[(i*4)]) ||
					(D1.memory[(i*4)+1] != D2.memory[(i*4)+1]) ||
					(D1.memory[(i*4)+2] != D2.memory[(i*4)+2]) ||
					(D1.memory[(i*4)+3] != D2.memory[(i*4)+3])
					) begin
					addi_w = 1;
				end
			end

			if (i == 10) begin
				if (
					(D1.memory[(i*4)] != D2.memory[(i*4)]) ||
					(D1.memory[(i*4)+1] != D2.memory[(i*4)+1]) ||
					(D1.memory[(i*4)+2] != D2.memory[(i*4)+2]) ||
					(D1.memory[(i*4)+3] != D2.memory[(i*4)+3])
					) begin
					slti_w = 1;
				end
			end

			if (i == 12) begin
				if (
					(D1.memory[(i*4)] != D2.memory[(i*4)]) ||
					(D1.memory[(i*4)+1] != D2.memory[(i*4)+1]) ||
					(D1.memory[(i*4)+2] != D2.memory[(i*4)+2]) ||
					(D1.memory[(i*4)+3] != D2.memory[(i*4)+3])
					) begin
					sw_w = 1;
				end
			end


			$display("%8d \t%X \t%X%X%X%X \t%X%X%X%X",
				i,
				i*4,
				D1.memory[(i*4)],
        D1.memory[(i*4)+1],
        D1.memory[(i*4)+2],
        D1.memory[(i*4)+3],

				D2.memory[(i*4)],
        D2.memory[(i*4)+1],
        D2.memory[(i*4)+2],
        D2.memory[(i*4)+3]
        );
			if ((!D1.memory[(i*4)]) && (!D1.memory[(i*4)+1]) && (!D1.memory[(i*4)+2]) && (!D1.memory[(i*4)+3]))
				j = j + 1;
			else
				j = 0;
			i = i + 1;
    end

		$display("\n\n");

		if (sw_w) $display("lw: wrong");
		else $display("lw: correct");
		if (sw_w) $display("sw: wrong");
		else $display("sw: correct");
		if (add_w) $display("add: wrong");
		else $display("add: correct");
		if (sub_w) $display("sub: wrong");
		else $display("sub: correct");
		if (slt_w) $display("slt: wrong");
		else $display("slt: correct");
		if (addi_w) $display("addi: wrong");
		else $display("addi: correct");
		if (slti_w) $display("slti: wrong");
		else $display("slti: correct");
		if (beq_w) $display("beq: wrong");
		else $display("beq: correct");
		if (bne_w) $display("bne: wrong");
		else $display("bne: correct");

		$finish;
	end
endmodule

lab3/sim/tb_proc.vcd
$date
	Tue Feb 28 22:40:20 2017
$end
$version
	Icarus Verilog
$end
$timescale
	1ps
$end
$scope module tb_single_cycle_mips $end
$var wire 32 ! inst_addr [31:0] $end
$var wire 32 " inst [31:0] $end
$var wire 1 # data_wr $end
$var wire 32 $ data_out [31:0] $end
$var wire 32 % data_in [31:0] $end
$var wire 32 & data_addr [31:0] $end
$var reg 1 ' clk $end
$var reg 1 ( rst_n $end
$var integer 32 ) add_w [31:0] $end
$var integer 32 * addi_w [31:0] $end
$var integer 32 + beq_w [31:0] $end
$var integer 32 , bne_w [31:0] $end
$var integer 32 - i [31:0] $end
$var integer 32 . j [31:0] $end
$var integer 32 / k [31:0] $end
$var integer 32 0 slt_w [31:0] $end
$var integer 32 1 slti_w [31:0] $end
$var integer 32 2 sub_w [31:0] $end
$var integer 32 3 sw_w [31:0] $end
$scope module D1 $end
$var wire 1 ' clk $end
$var wire 1 # data_wr $end
$var wire 32 4 data_out [31:0] $end
$var wire 32 5 data_addr [31:0] $end
$var reg 32 6 data_in [31:0] $end
$upscope $end
$scope module D2 $end
$upscope $end
$scope module I1 $end
$var wire 32 7 inst_addr [31:0] $end
$var reg 32 8 inst [31:0] $end
$upscope $end
$scope module UUT $end
$var wire 1 ' clk $end
$var wire 32 9 data_addr [31:0] $end
$var wire 32 : data_in [31:0] $end
$var wire 32 ; data_out [31:0] $end
$var wire 32 < inst [31:0] $end
$var wire 1 ( rst_n $end
$var wire 32 = rd_dataB [31:0] $end
$var wire 32 > rd_dataA [31:0] $end
$var wire 1 ? aluZ $end
$var wire 32 @ aluRes [31:0] $end
$var wire 1 A aluNeg $end
$var reg 32 B aluOpB [31:0] $end
$var reg 2 C aluSel [1:0] $end
$var reg 1 # data_wr $end
$var reg 6 D funct [5:0] $end
$var reg 32 E inst_addr [31:0] $end
$var reg 6 F opcode [5:0] $end
$var reg 5 G rd_addrA [4:0] $end
$var reg 5 H rd_addrB [4:0] $end
$var reg 5 I wr_addr [4:0] $end
$var reg 32 J wr_data [31:0] $end
$var reg 1 K wr_en $end
$scope module A1 $end
$var wire 1 L cout $end
$var wire 32 M opB [31:0] $end
$var wire 2 N sel [1:0] $end
$var wire 1 ? z $end
$var wire 32 O res_sub [31:0] $end
$var wire 32 P res_add [31:0] $end
$var wire 32 Q opA [31:0] $end
$var wire 1 A neg $end
$var reg 32 R res [31:0] $end
$upscope $end
$scope module R1 $end
$var wire 1 ' clk $end
$var wire 5 S rd_addrA [4:0] $end
$var wire 5 T rd_addrB [4:0] $end
$var wire 32 U rd_dataA [31:0] $end
$var wire 32 V rd_dataB [31:0] $end
$var wire 32 W reg1 [31:0] $end
$var wire 32 X reg10 [31:0] $end
$var wire 32 Y reg11 [31:0] $end
$var wire 32 Z reg12 [31:0] $end
$var wire 32 [ reg13 [31:0] $end
$var wire 32 \ reg14 [31:0] $end
$var wire 32 ] reg15 [31:0] $end
$var wire 32 ^ reg16 [31:0] $end
$var wire 32 _ reg17 [31:0] $end
$var wire 32 ` reg18 [31:0] $end
$var wire 32 a reg19 [31:0] $end
$var wire 32 b reg2 [31:0] $end
$var wire 32 c reg20 [31:0] $end
$var wire 32 d reg21 [31:0] $end
$var wire 32 e reg22 [31:0] $end
$var wire 32 f reg23 [31:0] $end
$var wire 32 g reg24 [31:0] $end
$var wire 32 h reg25 [31:0] $end
$var wire 32 i reg26 [31:0] $end
$var wire 32 j reg27 [31:0] $end
$var wire 32 k reg28 [31:0] $end
$var wire 32 l reg29 [31:0] $end
$var wire 32 m reg3 [31:0] $end
$var wire 32 n reg30 [31:0] $end
$var wire 32 o reg31 [31:0] $end
$var wire 32 p reg32 [31:0] $end
$var wire 32 q reg4 [31:0] $end
$var wire 32 r reg5 [31:0] $end
$var wire 32 s reg6 [31:0] $end
$var wire 32 t reg7 [31:0] $end
$var wire 32 u reg8 [31:0] $end
$var wire 32 v reg9 [31:0] $end
$var wire 1 ( rst_n $end
$var wire 5 w wr_addr [4:0] $end
$var wire 32 x wr_data [31:0] $end
$var wire 1 K wr_en $end
$upscope $end
$upscope $end
$upscope $end
$enddefinitions $end
#0
$dumpvars
b10010001101000101011001111000 x
b1 w
b0 v
b0 u
b0 t
b0 s
b0 r
b0 q
b0 p
b0 o
b0 n
b0 m
b0 l
b0 k
b0 j
b0 i
b0 h
b0 g
b0 f
b0 e
b0 d
b0 c
b0 b
b0 a
b0 `
b0 _
b0 ^
b0 ]
b0 \
b0 [
b0 Z
b0 Y
b0 X
b0 W
b0 V
b0 U
b1 T
b0 S
b111000 R
b0 Q
b111000 P
b11111111111111111111111111001000 O
b0 N
b111000 M
0L
1K
b10010001101000101011001111000 J
b1 I
b1 H
b0 G
b100011 F
b0 E
b111000 D
b0 C
b111000 B
0A
b111000 @
0?
b0 >
b0 =
b10001100000000010000000000111000 <
b0 ;
b10010001101000101011001111000 :
b111000 9
b10001100000000010000000000111000 8
b0 7
b10010001101000101011001111000 6
b111000 5
b0 4
b0 3
b0 2
b0 1
b0 0
b0 /
b0 .
b0 -
b0 ,
b0 +
b0 *
b0 )
0(
0'
b111000 &
b10010001101000101011001111000 %
b0 $
0#
b10001100000000010000000000111000 "
b0 !
$end
#25000
1'
#28000
1(
#50000
0'
#75000
b0 %
b0 6
b0 :
b101100 &
b101100 5
b101100 9
b101100 @
b101100 R
0K
1#
b11111111111111111111111111010100 O
b101100 P
b101100 B
b101100 M
b101011 F
b101100 D
b10101100000000010000000000101100 "
b10101100000000010000000000101100 8
b10101100000000010000000000101100 <
b10010001101000101011001111000 $
b10010001101000101011001111000 4
b10010001101000101011001111000 ;
b10010001101000101011001111000 =
b10010001101000101011001111000 V
b10010001101000101011001111000 b
b100 !
b100 7
b100 E
1'
#100000
0'
#125000
b10001001000100011001101000100 J
b10001001000100011001101000100 x
b111100 &
b111100 5
b111100 9
b111100 @
b111100 R
0#
1K
b11111111111111111111111111000100 O
b111100 P
b111100 B
b111100 M
b1000 I
b1000 w
b111100 D
b100011 F
b0 $
b0 4
b0 ;
b0 =
b0 V
b1000 H
b1000 T
b10001001000100011001101000100 %
b10001001000100011001101000100 6
b10001001000100011001101000100 :
b10001100000010000000000000111100 "
b10001100000010000000000000111100 8
b10001100000010000000000000111100 <
b1000 !
b1000 7
b1000 E
1'
#150000
0'
#175000
b100010001100110100010001010101 J
b100010001100110100010001010101 x
b100010001100110100010001010101 %
b100010001100110100010001010101 6
b100010001100110100010001010101 :
b1000000 &
b1000000 5
b1000000 9
b1000000 @
b1000000 R
b11111111111111111111111111000000 O
b1000000 P
b1000000 B
b1000000 M
b1001 I
b1001 w
b1001 H
b1001 T
b0 D
b10001100000010010000000001000000 "
b10001100000010010000000001000000 8
b10001100000010010000000001000000 <
b0 $
b0 4
b0 ;
b0 =
b0 V
b10001001000100011001101000100 v
b1100 !
b1100 7
b1100 E
1'
#200000
0'
#225000
b11111111 J
b11111111 x
b11111111 %
b11111111 6
b11111111 :
b1000100 &
b1000100 5
b1000100 9
b1000100 @
b1000100 R
b11111111111111111111111110111100 O
b1000100 P
b1000100 B
b1000100 M
b1010 I
b1010 w
b100 D
b1010 H
b1010 T
b10001100000010100000000001000100 "
b10001100000010100000000001000100 8
b10001100000010100000000001000100 <
b10000 !
b10000 7
b10000 E
b0 $
b0 4
b0 ;
b0 =
b0 V
b100010001100110100010001010101 X
1'
#250000
0'
#275000
bx %
bx 6
bx :
b110011010101010111011110011001 &
b110011010101010111011110011001 5
b110011010101010111011110011001 9
b110011010101010111011110011001 @
b110011010101010111011110011001 R
b110011010101010111011110011001 J
b110011010101010111011110011001 x
0A
b11101110111011101110111011101111 O
0L
b110011010101010111011110011001 P
b100010001100110100010001010101 B
b100010001100110100010001010101 M
b10000 I
b10000 w
b10001001000100011001101000100 >
b10001001000100011001101000100 Q
b10001001000100011001101000100 U
b1000 G
b1000 S
b1001 H
b1001 T
b0 F
b100000 D
b1000010011000000000100000 "
b1000010011000000000100000 8
b1000010011000000000100000 <
b100010001100110100010001010101 $
b100010001100110100010001010101 4
b100010001100110100010001010101 ;
b100010001100110100010001010101 =
b100010001100110100010001010101 V
b11111111 Y
b10100 !
b10100 7
b10100 E
1'
#300000
0'
#325000
b0 %
b0 6
b0 :
b11000 &
b11000 5
b11000 9
b11000 @
b11000 R
1#
0K
b11000 B
b11000 M
b11111111111111111111111111101000 O
b11000 P
b10000 I
b10000 w
b11000 D
b101011 F
b110011010101010111011110011001 $
b110011010101010111011110011001 4
b110011010101010111011110011001 ;
b110011010101010111011110011001 =
b110011010101010111011110011001 V
b10000 H
b10000 T
b0 >
b0 Q
b0 U
b0 G
b0 S
b10101100000100000000000000011000 "
b10101100000100000000000000011000 8
b10101100000100000000000000011000 <
b11000 !
b11000 7
b11000 E
b110011010101010111011110011001 _
1'
#350000
0'
#375000
b10001000100010001000100010001 &
b10001000100010001000100010001 5
b10001000100010001000100010001 9
b10001000100010001000100010001 @
b10001000100010001000100010001 R
1K
0#
b10001000100010001000100010001 J
b10001000100010001000100010001 x
b1 C
b1 N
0A
b10001000100010001000100010001 O
xL
b110011010101010111011110011001 P
b10001001000100011001101000100 B
b10001001000100011001101000100 M
b10000 I
b10000 w
b100010001100110100010001010101 >
b100010001100110100010001010101 Q
b100010001100110100010001010101 U
b1001 G
b1001 S
b10001001000100011001101000100 $
b10001001000100011001101000100 4
b10001001000100011001101000100 ;
b10001001000100011001101000100 =
b10001001000100011001101000100 V
b1000 H
b1000 T
b0 F
b100010 D
bx %
bx 6
bx :
b1001010001000000000100010 "
b1001010001000000000100010 8
b1001010001000000000100010 <
b11100 !
b11100 7
b11100 E
1'
#400000
0'
#425000
b0 %
b0 6
b0 :
b11100 &
b11100 5
b11100 9
b11100 @
b11100 R
1#
0K
b0 C
b0 N
b11100 B
b11100 M
b11111111111111111111111111100100 O
0L
b11100 P
b10000 I
b10000 w
b11100 D
b101011 F
b10001000100010001000100010001 $
b10001000100010001000100010001 4
b10001000100010001000100010001 ;
b10001000100010001000100010001 =
b10001000100010001000100010001 V
b10000 H
b10000 T
b0 >
b0 Q
b0 U
b0 G
b0 S
b10101100000100000000000000011100 "
b10101100000100000000000000011100 8
b10101100000100000000000000011100 <
b100000 !
b100000 7
b100000 E
b10001000100010001000100010001 _
1'
#450000
0'
#475000
b11101110111011101110111011101111 &
b11101110111011101110111011101111 5
b11101110111011101110111011101111 9
b11101110111011101110111011101111 @
b11101110111011101110111011101111 R
1K
0#
b1 J
b1 x
b1 C
b1 N
0A
b11101110111011101110111011101111 O
0L
b110011010101010111011110011001 P
b100010001100110100010001010101 B
b100010001100110100010001010101 M
b10000 I
b10000 w
b10001001000100011001101000100 >
b10001001000100011001101000100 Q
b10001001000100011001101000100 U
b1000 G
b1000 S
b100010001100110100010001010101 $
b100010001100110100010001010101 4
b100010001100110100010001010101 ;
b100010001100110100010001010101 =
b100010001100110100010001010101 V
b1001 H
b1001 T
b0 F
b101010 D
bx %
bx 6
bx :
b1000010011000000000101010 "
b1000010011000000000101010 8
b1000010011000000000101010 <
b100100 !
b100100 7
b100100 E
1'
#500000
0'
#525000
b0 %
b0 6
b0 :
b100000 &
b100000 5
b100000 9
b100000 @
b100000 R
1#
0K
b0 C
b0 N
b100000 B
b100000 M
b11111111111111111111111111100000 O
b100000 P
b10000 I
b10000 w
b100000 D
b101011 F
b1 $
b1 4
b1 ;
b1 =
b1 V
b10000 H
b10000 T
b0 >
b0 Q
b0 U
b0 G
b0 S
b10101100000100000000000000100000 "
b10101100000100000000000000100000 8
b10101100000100000000000000100000 <
b101000 !
b101000 7
b101000 E
b1 _
1'
#550000
0'
#575000
b10001001000100101101001010100 &
b10001001000100101101001010100 5
b10001001000100101101001010100 9
b10001001000100101101001010100 @
b10001001000100101101001010100 R
1K
0#
b10001001000100101101001010100 J
b10001001000100101101001010100 x
0A
b10001001000100000110000110100 O
xL
b10001001000100101101001010100 P
b10011100010000 B
b10011100010000 M
b10001001000100011001101000100 >
b10001001000100011001101000100 Q
b10001001000100011001101000100 U
b1000 G
b1000 S
b1000 F
b10000 D
bx %
bx 6
bx :
b100001000100000010011100010000 "
b100001000100000010011100010000 8
b100001000100000010011100010000 <
b101100 !
b101100 7
b101100 E
1'
#600000
0'
#625000
b0 %
b0 6
b0 :
b100100 &
b100100 5
b100100 9
b100100 @
b100100 R
1#
0K
b11111111111111111111111111011100 O
0L
b100100 P
b100100 B
b100100 M
b100100 D
b101011 F
b0 >
b0 Q
b0 U
b0 G
b0 S
b10101100000100000000000000100100 "
b10101100000100000000000000100100 8
b10101100000100000000000000100100 <
b110000 !
b110000 7
b110000 E
b10001001000100101101001010100 $
b10001001000100101101001010100 4
b10001001000100101101001010100 ;
b10001001000100101101001010100 =
b10001001000100101101001010100 V
b10001001000100101101001010100 _
1'
#650000
0'
#675000
b11111111111111111111000100000000 &
b11111111111111111111000100000000 5
b11111111111111111111000100000000 9
b11111111111111111111000100000000 @
b11111111111111111111000100000000 R
1K
0#
b1 J
b1 x
b1 C
b1 N
0A
b11111111111111111111000100000000 O
0L
b1000011111110 P
b111111111111 B
b111111111111 M
b11111111 >
b11111111 Q
b11111111 U
b1010 G
b1010 S
b1010 F
b111111 D
bx %
bx 6
bx :
b101001010100000000111111111111 "
b101001010100000000111111111111 8
b101001010100000000111111111111 <
b110100 !
b110100 7
b110100 E
1'
#700000
0'
#725000
b0 %
b0 6
b0 :
b101000 &
b101000 5
b101000 9
b101000 @
b101000 R
1#
0K
b0 C
b0 N
b11111111111111111111111111011000 O
b101000 P
b101000 B
b101000 M
b101000 D
b101011 F
b0 >
b0 Q
b0 U
b0 G
b0 S
b10101100000100000000000000101000 "
b10101100000100000000000000101000 8
b10101100000100000000000000101000 <
b111000 !
b111000 7
b111000 E
b1 $
b1 4
b1 ;
b1 =
b1 V
b1 _
1'
#750000
0'
