coe113_2016_lab4_checker/sim/datamem.v
`timescale 1ns/1ps
`define MEM_DEPTH  1024
`define MEM_WIDTH  8
`define WORD_WIDTH 32
`include "defines.h"
module datamem(
  clk,
  data_addr,
  data_wr,
  data_in, //input to processor
  data_out //output of processor
  );
  input clk,data_wr;
  input [`WORD_WIDTH-1:0] data_addr,data_out;
  output [`WORD_WIDTH-1:0] data_in;

  reg [`MEM_WIDTH-1:0] memory [0:`MEM_DEPTH-1];

  initial begin
    $readmemh("../asm/datamem.txt",memory);
  end

  //Read port
  reg [`WORD_WIDTH-1:0] data_in_temp;

  always@(posedge clk)
    data_in_temp = {memory[data_addr],
    //data_in <= {memory[data_addr],
                memory[data_addr+1],
                memory[data_addr+2],
                memory[data_addr+3]};
  assign #(`INPUT_DELAY) data_in = data_in_temp;

  //Write port
  always@(posedge clk)
    if (data_wr) begin
      memory[data_addr] <= data_out[31:24];
      memory[data_addr+1] <= data_out[23:16];
      memory[data_addr+2] <= data_out[15:8];
      memory[data_addr+3] <= data_out[7:0];
    end
endmodule

coe113_2016_lab4_checker/sim/instmem.v
`timescale 1ns/1ps
`define MEM_DEPTH  1024
`define MEM_WIDTH  8
`define WORD_WIDTH 32
`include "defines.h"
module instmem(
  clk,
  inst_addr,
  inst
  );
  input clk;
  input [`WORD_WIDTH-1:0] inst_addr;
  output [`WORD_WIDTH-1:0] inst;

  reg [`MEM_WIDTH-1:0] memory [0:`MEM_DEPTH-1];

  initial begin
    //$readmemh("instmem.txt",memory);
    //$readmemh("./assembler/instmem.txt",memory);
    //$readmemh("../asm/source1.byte",memory);
    //$readmemh("../asm/temp.byte",memory);
    $readmemh("../asm/test.byte",memory);
  end

  //Read port
  reg [`WORD_WIDTH-1:0] inst_temp;

  always@(posedge clk)
    inst_temp = {memory[inst_addr],
    //inst <= {memory[inst_addr],
             memory[inst_addr+1],
             memory[inst_addr+2],
             memory[inst_addr+3]};

  assign #(`INPUT_DELAY) inst = inst_temp;

endmodule

checker/rtl/alu.v
`timescale 1ns/1ps
`define WORD_WIDTH 32

module alu ( opA, opB, sel, res, z, neg );
	input [`WORD_WIDTH-1:0] opA;
	input [`WORD_WIDTH-1:0]	opB;
	input [1:0] sel;	
	output reg [31:0] res;
	output z;
	output neg;

	wire [`WORD_WIDTH-1:0] res_add;
	wire [`WORD_WIDTH-1:0] res_sub;
	wire cout;

	assign {cout, res_add} = {1'b0, opA} + {1'b0, opB};
	assign {cout, res_sub} = {1'b0, opA} + {1'b0, ~opB} + 1'b1;

	/* res output */
	always @ (*)
		case (sel)
			2'd0: res <= res_add;
			2'd1: res <= res_sub;			
		endcase

	/* zero flag */
	assign z = (res == 0) ? 1'b1 : 1'b0;

	/* negative number flag */
	assign neg = ((cout == 1'b1) && (res_sub[31] == 1'b1)) ? 1'b1 : 1'b0;

endmodule

lab3/rtl/rf.v
`timescale 1ns/1ps
`define MEM_DEPTH  32
`define MEM_WIDTH  32
`define WORD_WIDTH 32

module rf(
	input clk,
	input rst_n,
	input [4:0] rd_addrA,
	input [4:0] rd_addrB,
	output [`WORD_WIDTH-1:0] rd_dataA,
	output [`WORD_WIDTH-1:0] rd_dataB,
	input wr_en,
	input [4:0] wr_addr,
	input [`WORD_WIDTH-1:0] wr_data
);

	reg [`MEM_WIDTH-1:0] regf [`MEM_DEPTH-1:0];
	
	wire [31:0] reg1;
	wire [31:0] reg2;
	wire [31:0] reg3;
	wire [31:0] reg4;
	wire [31:0] reg5;
	wire [31:0] reg6;
	wire [31:0] reg7;
	wire [31:0] reg8;
	wire [31:0] reg9;
	wire [31:0] reg10;
	wire [31:0] reg11;
	wire [31:0] reg12;
	wire [31:0] reg13;
	wire [31:0] reg14;
	wire [31:0] reg15;
	wire [31:0] reg16;
	wire [31:0] reg17;
	wire [31:0] reg18;
	wire [31:0] reg19;
	wire [31:0] reg20;
	wire [31:0] reg21;
	wire [31:0] reg22;
	wire [31:0] reg23;
	wire [31:0] reg24;
	wire [31:0] reg25;
	wire [31:0] reg26;
	wire [31:0] reg27;
	wire [31:0] reg28;
	wire [31:0] reg29;
	wire [31:0] reg30;
	wire [31:0] reg31;
	wire [31:0] reg32;

	assign reg1 = regf[0];
	assign reg2 = regf[1];
	assign reg3 = regf[2];
	assign reg4 = regf[3];
	assign reg5 = regf[4];
	assign reg6 = regf[5];
	assign reg7 = regf[6];
	assign reg8 = regf[7];
	assign reg9 = regf[8];
	assign reg10 = regf[9];
	assign reg11 = regf[10];
	assign reg12 = regf[11];
	assign reg13 = regf[12];
	assign reg14 = regf[13];
	assign reg15 = regf[14];
	assign reg16 = regf[15];
	assign reg17 = regf[16];
	assign reg18 = regf[17];
	assign reg19 = regf[18];
	assign reg20 = regf[19];
	assign reg21 = regf[20];
	assign reg22 = regf[21];
	assign reg23 = regf[22];
	assign reg24 = regf[23];
	assign reg25 = regf[24];
	assign reg26 = regf[25];
	assign reg27 = regf[26];
	assign reg28 = regf[27];
	assign reg29 = regf[28];
	assign reg30 = regf[29];
	assign reg31 = regf[30];
	assign reg32 = regf[31];


	always @ (posedge clk, negedge rst_n)
		if (!rst_n) begin
			regf[0] <= 32'd0;
			regf[1] <= 32'd0;
			regf[2] <= 32'd0;
			regf[3] <= 32'd0;
			regf[4] <= 32'd0;
			regf[5] <= 32'd0;
			regf[6] <= 32'd0;
			regf[7] <= 32'd0;
			regf[8] <= 32'd0;
			regf[9] <= 32'd0;
			regf[10] <= 32'd0;
			regf[11] <= 32'd0;
			regf[12] <= 32'd0;
			regf[13] <= 32'd0;
			regf[14] <= 32'd0;
			regf[15] <= 32'd0;
			regf[16] <= 32'd0;
			regf[17] <= 32'd0;
			regf[18] <= 32'd0;
			regf[19] <= 32'd0;
			regf[20] <= 32'd0;
			regf[21] <= 32'd0;
			regf[22] <= 32'd0;
			regf[23] <= 32'd0;
			regf[24] <= 32'd0;
			regf[25] <= 32'd0;
			regf[26] <= 32'd0;
			regf[27] <= 32'd0;
			regf[28] <= 32'd0;
			regf[29] <= 32'd0;
			regf[30] <= 32'd0;
			regf[31] <= 32'd0;
		end
		else
			if (wr_en)
				case (wr_addr)
					5'd0: regf[wr_addr] <= 0;
					default: regf[wr_addr] <= wr_data;
				endcase

	assign rd_dataA = regf[rd_addrA];
	assign rd_dataB = regf[rd_addrB];

endmodule

lab3/rtl/single_cycle_mips.v
module single_cycle_mips ( clk, rst_n, inst_addr, inst, data_addr, data_in,
        data_out, data_wr );
  output [31:0] inst_addr;
  input [31:0] inst;
  output [31:0] data_addr;
  input [31:0] data_in;
  output [31:0] data_out;
  input clk, rst_n;
  output reg data_wr;

  parameter instBEQ = 6'b000100;
  parameter instBNE = 6'b000101;
  parameter instADDI = 6'b001000;
  parameter instSLTI = 6'b001010;
  parameter instSW = 6'b101011;
  parameter instLW = 6'b100011;

  parameter instRType = 6'd0;

  parameter functADD = 6'b100000;
  parameter functSUB = 6'b100010;
  parameter functSLT = 6'b101010;

	reg [4:0] rd_addrA;
	reg [4:0] rd_addrB;
	wire [31:0] rd_dataA;
	wire [31:0] rd_dataB;
	reg wr_en;
	reg [4:0] wr_addr;
	reg [31:0] wr_data;
	reg [5:0] opcode;
	reg [5:0] funct;

	/* Register File */
	rf R1 (.clk(clk),
		.rst_n(rst_n),
		.rd_addrA(rd_addrA),
		.rd_addrB(rd_addrB),
		.rd_dataA(rd_dataA),
		.rd_dataB(rd_dataB),
		.wr_en(wr_en),
		.wr_addr(wr_addr),
		.wr_data(wr_data)
	);

	/* Program Counter */
	reg [31:0] inst_addr;

	reg [`WORD_WIDTH-1:0] aluOpB;
	reg [1:0] aluSel;
	wire [`WORD_WIDTH-1:0] aluRes;
	wire aluZ;
	wire aluNeg;

	/* ALU */
	alu A1 (.opA(rd_dataA),
		.opB(aluOpB),
		.sel(aluSel),
		.res(aluRes),
		.z(aluZ),
		.neg(aluNeg)
	);

  always @ (*)
    rd_addrA <= inst[25:21];

  always @ (*)
    rd_addrB <= inst[20:16];

  always @ (*)
    opcode <= inst[31:26];

  always @ (*)
    funct <= inst[5:0];

	always @ (posedge clk, negedge rst_n)
		if (!rst_n)
			inst_addr <= 0;
		else
      case (opcode)
        instBEQ:
          if (aluZ)
            inst_addr <= (inst_addr + 4) + { {15{inst[15]}}, inst[15:0], 2'b0 };
          else
            inst_addr <= inst_addr + 4;
        instBNE:
          if (!aluZ)
            inst_addr <= (inst_addr + 4) + { {15{inst[15]}}, inst[15:0], 2'b0 };
          else
            inst_addr <= inst_addr + 4;
        default:
            inst_addr <= inst_addr + 4;
      endcase

	/* wr_addr input multiplexer for the reg file */
	always @ (*)
		case (opcode)
      instRType:
				wr_addr <= inst[15:11];		// rd
      instADDI,
      instSLTI,
      instSW,
      instLW:
				wr_addr <= inst[20:16];		// rt
			default:
				wr_addr <= inst[15:11];
		endcase

	/* wr_en control signal for reg file */
	always @ (*)
		case (opcode)
      instRType,
      instADDI,
      instSLTI,
      instLW:
				wr_en <= 1'b1;
			default:
				wr_en <= 1'b0;
		endcase

	/* aluOpB input multiplexer for the ALU */
	always @ (*)
		case (opcode)
      instRType:
				aluOpB <= rd_dataB;
      instADDI,
      instSLTI,
      instSW,
      instLW:
				aluOpB <= { {16{inst[15]}}, inst[15:0] };		// sign extend
			default:
				aluOpB <= rd_dataB;
		endcase

	parameter aluAdd = 2'd0;
	parameter aluSub = 2'd1;

	/* aluSel control signal for ALU */
	always @ (*)
		case (opcode)
      instRType:
				case (funct)
          functADD:
						aluSel <= aluAdd;
          functSUB,
          functSLT:
						aluSel <= aluSub;
					//default:
						//aluSel <= ???
				endcase
      instADDI,
      instSW,
      instLW:
				aluSel <= aluAdd;
      instBEQ,
      instBNE,
      instSLTI:
				aluSel <= aluSub;
		endcase

	/* data_wr control signal for the data memory */
	always @ (*)
		case (opcode)
      instSW:
				data_wr <= 1'b1;
			default:
				data_wr <= 1'b0;
		endcase

	/* wr_data input control signal for the reg file */
	always @ (*)
		case (opcode)
      instRType:
				case (funct)
          functSLT:
						wr_data <= 32'd1;
					default:
						wr_data <= aluRes;
				endcase
      instADDI:
				wr_data <= aluRes;
      instSLTI:
				wr_data <= 32'd1;
      instLW:
				wr_data <= data_in;
		endcase


	assign data_out = rd_dataB;
	assign data_addr = aluRes;
endmodule

coe113_2016_lab4_checker/sim/tb_pipelined_mips.v
`timescale 1ns/1ps
//`define CLK_PERIOD 20
`include "defines.h"
`define TIMEOUT 9
`define WATCHDOG 500
module tb_pipelined_mips;

  reg clk,rst_n;
  wire [31:0] inst_addr,inst;
  wire [31:0] data_addr,data_in,data_out;
  wire data_wr;
  wire [31:0] pc_if,pc_id,pc_exe,pc_mem,pc_wb;

  assign pc_if = inst_addr;
  single_cycle_mips UUT(
    .clk(clk),
    .rst_n(rst_n),
    .inst_addr(inst_addr),
    .inst(inst),
    .data_addr(data_addr),
    .data_in(data_in),
    .data_out(data_out),
    .data_wr(data_wr)//,
    //debug
    // .pc_id(pc_id),
    // .pc_exe(pc_exe),
    // .pc_mem(pc_mem),
    // .pc_wb(pc_wb)
  );

  instmem INSTMEM(
    .clk(clk),
    .inst_addr(inst_addr),
    .inst(inst)
  );

  datamem DATAMEM(
    .clk(clk),
    .data_addr(data_addr),
    .data_wr(data_wr),
    .data_in(data_in),
    .data_out(data_out)
  );

  always begin
    #(`CLK_PERIOD/2.0) clk = ~clk;
  end

  integer nop_count,watch_count,i;
  integer ldst,add,sub,slt,beq,bne;
  reg [31:0] ref [0:127];
  reg [31:0] res;
  initial begin
    // $vcdplusfile("tb_pipelined_mips.vpd");
    // $vcdpluson;
    $dumpfile("tb_pipelined_mips.vcd");
    $dumpvars;

    //init
    clk = 0;
    rst_n = 0;
    nop_count = 0;
    watch_count = 0;

    #(`CLK_PERIOD*10);
    #(`CLK_PERIOD*0.8);
    rst_n = 1'b1;

    //start
    while((nop_count < `TIMEOUT)&&(watch_count < `WATCHDOG))begin
      #(`CLK_PERIOD);
      if (inst == 32'd0)
        nop_count = nop_count + 1;
      else
        nop_count = 0;
      watch_count = watch_count + 1;
    end

    ldst = 0;
    add = 0;
    sub = 0;
    slt = 0;
    beq = 0;
    bne = 0;

    //display mem
    for (i=0; i<27; i=i+1) begin
      $display("%X%X%X%X",
        DATAMEM.memory[(i*4)],
        DATAMEM.memory[(i*4)+1],
        DATAMEM.memory[(i*4)+2],
        DATAMEM.memory[(i*4)+3],
        );
      res = {DATAMEM.memory[(i*4)],
             DATAMEM.memory[(i*4)+1],
             DATAMEM.memory[(i*4)+2],
             DATAMEM.memory[(i*4)+3]};
      case(i)
        3,4,6:
          if (res == ref[i]) ldst = ldst + 1;
        7,8,9,10:
          if (res == ref[i]) add = add + 1;
        11,12,13,14,21:
          if (res == ref[i]) beq = beq + 1;
        15,16,17,18:
          if (res == ref[i]) sub = sub + 1;
        19,20:
          if (res == ref[i]) slt = slt + 1;
        22,23,24,25,26:
          if (res == ref[i]) bne = bne + 1;
      endcase
    end

    $display("Load/Store: %d / 3",ldst);
    $display("ADD: %d / 4",add);
    $display("SUB: %d / 4",sub);
    $display("SLT: %d / 2",slt);
    $display("BEQ: %d / 5",beq);
    $display("BNE: %d / 5",bne);

    //display regfile
    /*$display("R1: %x",UUT.STAGE_2.RF.elem01);
    $display("R2: %x",UUT.STAGE_2.RF.elem02);
    $display("R3: %x",UUT.STAGE_2.RF.elem03);
    $display("R4: %d",UUT.STAGE_2.RF.elem04);
    $display("R5: %d",UUT.STAGE_2.RF.elem05);
    $display("R6: %d",UUT.STAGE_2.RF.elem06);
    */

    $finish;
  end

  initial begin
    $readmemh("./ref.txt",ref);
  end

`ifdef SDF
  initial begin
    $sdf_annotate("../check/mapped/pipelined_mips_mapped.sdf",pipelined_mips);
  end
`endif

endmodule

coe113_2016_lab4_checker/sim/tb_pipelined_mips.vcd
$date
	Sun Apr  2 13:31:30 2017
$end
$version
	Icarus Verilog
$end
$timescale
	1ps
$end
$scope module tb_pipelined_mips $end
$var wire 32 ! pc_if [31:0] $end
$var wire 32 " inst_addr [31:0] $end
$var wire 32 # inst [31:0] $end
$var wire 1 $ data_wr $end
$var wire 32 % data_out [31:0] $end
$var wire 32 & data_in [31:0] $end
$var wire 32 ' data_addr [31:0] $end
$var reg 1 ( clk $end
$var reg 32 ) res [31:0] $end
$var reg 1 * rst_n $end
$var integer 32 + add [31:0] $end
$var integer 32 , beq [31:0] $end
$var integer 32 - bne [31:0] $end
$var integer 32 . i [31:0] $end
$var integer 32 / ldst [31:0] $end
$var integer 32 0 nop_count [31:0] $end
$var integer 32 1 slt [31:0] $end
$var integer 32 2 sub [31:0] $end
$var integer 32 3 watch_count [31:0] $end
$scope module DATAMEM $end
$var wire 1 ( clk $end
$var wire 32 4 data_in [31:0] $end
$var wire 1 $ data_wr $end
$var wire 32 5 data_out [31:0] $end
$var wire 32 6 data_addr [31:0] $end
$var reg 32 7 data_in_temp [31:0] $end
$upscope $end
$scope module INSTMEM $end
$var wire 1 ( clk $end
$var wire 32 8 inst [31:0] $end
$var wire 32 9 inst_addr [31:0] $end
$var reg 32 : inst_temp [31:0] $end
$upscope $end
$scope module UUT $end
$var wire 1 ( clk $end
$var wire 32 ; data_addr [31:0] $end
$var wire 32 < data_in [31:0] $end
$var wire 32 = data_out [31:0] $end
$var wire 32 > inst [31:0] $end
$var wire 1 * rst_n $end
$var wire 32 ? rd_dataB [31:0] $end
$var wire 32 @ rd_dataA [31:0] $end
$var wire 1 A aluZ $end
$var wire 32 B aluRes [31:0] $end
$var wire 1 C aluNeg $end
$var reg 32 D aluOpB [31:0] $end
$var reg 2 E aluSel [1:0] $end
$var reg 1 $ data_wr $end
$var reg 6 F funct [5:0] $end
$var reg 32 G inst_addr [31:0] $end
$var reg 6 H opcode [5:0] $end
$var reg 5 I rd_addrA [4:0] $end
$var reg 5 J rd_addrB [4:0] $end
$var reg 5 K wr_addr [4:0] $end
$var reg 32 L wr_data [31:0] $end
$var reg 1 M wr_en $end
$scope module A1 $end
$var wire 1 N cout $end
$var wire 32 O opB [31:0] $end
$var wire 2 P sel [1:0] $end
$var wire 1 A z $end
$var wire 32 Q res_sub [31:0] $end
$var wire 32 R res_add [31:0] $end
$var wire 32 S opA [31:0] $end
$var wire 1 C neg $end
$var reg 32 T res [31:0] $end
$upscope $end
$scope module R1 $end
$var wire 1 ( clk $end
$var wire 5 U rd_addrA [4:0] $end
$var wire 5 V rd_addrB [4:0] $end
$var wire 32 W rd_dataA [31:0] $end
$var wire 32 X rd_dataB [31:0] $end
$var wire 32 Y reg1 [31:0] $end
$var wire 32 Z reg10 [31:0] $end
$var wire 32 [ reg11 [31:0] $end
$var wire 32 \ reg12 [31:0] $end
$var wire 32 ] reg13 [31:0] $end
$var wire 32 ^ reg14 [31:0] $end
$var wire 32 _ reg15 [31:0] $end
$var wire 32 ` reg16 [31:0] $end
$var wire 32 a reg17 [31:0] $end
$var wire 32 b reg18 [31:0] $end
$var wire 32 c reg19 [31:0] $end
$var wire 32 d reg2 [31:0] $end
$var wire 32 e reg20 [31:0] $end
$var wire 32 f reg21 [31:0] $end
$var wire 32 g reg22 [31:0] $end
$var wire 32 h reg23 [31:0] $end
$var wire 32 i reg24 [31:0] $end
$var wire 32 j reg25 [31:0] $end
$var wire 32 k reg26 [31:0] $end
$var wire 32 l reg27 [31:0] $end
$var wire 32 m reg28 [31:0] $end
$var wire 32 n reg29 [31:0] $end
$var wire 32 o reg3 [31:0] $end
$var wire 32 p reg30 [31:0] $end
$var wire 32 q reg31 [31:0] $end
$var wire 32 r reg32 [31:0] $end
$var wire 32 s reg4 [31:0] $end
$var wire 32 t reg5 [31:0] $end
$var wire 32 u reg6 [31:0] $end
$var wire 32 v reg7 [31:0] $end
$var wire 32 w reg8 [31:0] $end
$var wire 32 x reg9 [31:0] $end
$var wire 1 * rst_n $end
$var wire 5 y wr_addr [4:0] $end
$var wire 32 z wr_data [31:0] $end
$var wire 1 M wr_en $end
$upscope $end
$upscope $end
$upscope $end
$enddefinitions $end
#0
$dumpvars
bx z
bx y
b0 x
b0 w
b0 v
b0 u
b0 t
b0 s
b0 r
b0 q
b0 p
b0 o
b0 n
b0 m
b0 l
b0 k
b0 j
b0 i
b0 h
b0 g
b0 f
b0 e
b0 d
b0 c
b0 b
b0 a
b0 `
b0 _
b0 ^
b0 ]
b0 \
b0 [
b0 Z
b0 Y
bx X
bx W
bx V
bx U
bx T
bx S
bx R
bx Q
bx P
bx O
xN
xM
bx L
bx K
bx J
bx I
bx H
b0 G
bx F
bx E
bx D
xC
bx B
xA
bx @
bx ?
bx >
bx =
bx <
bx ;
bx :
b0 9
bx 8
bx 7
bx 6
bx 5
bx 4
b0 3
bx 2
bx 1
b0 0
bx /
bx .
bx -
bx ,
bx +
0*
bx )
0(
bx '
bx &
bx %
x$
bx #
b0 "
b0 !
$end
#25000
1A
b0 '
b0 6
b0 ;
b0 B
b0 T
0C
b0 Q
b0 R
0$
1M
b0 E
b0 P
b0 D
b0 O
b1 K
b1 y
b0 F
b100011 H
b0 %
b0 5
b0 =
b0 ?
b0 X
b1 J
b1 V
b0 @
b0 S
b0 W
b0 I
b0 U
b10001100000000010000000000000000 #
b10001100000000010000000000000000 8
b10001100000000010000000000000000 >
b10001100000000010000000000000000 :
1(
#50000
0(
#75000
b100011010101111001101 L
b100011010101111001101 z
b100011010101111001101 &
b100011010101111001101 4
b100011010101111001101 <
b100011010101111001101 7
1(
#100000
0(
#125000
1(
#150000
0(
#175000
1(
#200000
0(
#225000
1(
#250000
0(
#275000
1(
#300000
0(
#325000
1(
#350000
0(
#375000
1(
#400000
0(
#425000
1(
#450000
0(
#475000
1(
#500000
0(
#525000
1(
#540000
1*
#550000
0(
#575000
b100011010101111001101 %
b100011010101111001101 5
b100011010101111001101 =
b100011010101111001101 ?
b100011010101111001101 X
b100011010101111001101 d
b100 !
b100 "
b100 9
b100 G
1(
#590000
b1 3
#600000
0(
#625000
0A
b100 '
b100 6
b100 ;
b100 B
b100 T
b11111111111111111111111111111100 Q
0N
b100 R
b100 D
b100 O
b10 K
b10 y
b0 %
b0 5
b0 =
b0 ?
b0 X
b10 J
b10 V
b100 F
b1000 !
b1000 "
b1000 9
b1000 G
b10001100000000100000000000000100 #
b10001100000000100000000000000100 8
b10001100000000100000000000000100 >
b10001100000000100000000000000100 :
1(
#640000
b10 3
#650000
0(
#675000
b1000 '
b1000 6
b1000 ;
b1000 B
b1000 T
b11111111111111111111111111111000 Q
b1000 R
b11111111111111110000000100000001 L
b11111111111111110000000100000001 z
b1000 D
b1000 O
b11 K
b11 y
b1000 F
b11 J
b11 V
b0 %
b0 5
b0 =
b0 ?
b0 X
b100011010101111001101 o
b1100 !
b1100 "
b1100 9
b1100 G
b11111111111111110000000100000001 &
b11111111111111110000000100000001 4
b11111111111111110000000100000001 <
b11111111111111110000000100000001 7
b10001100000000110000000000001000 #
b10001100000000110000000000001000 8
b10001100000000110000000000001000 >
b10001100000000110000000000001000 :
1(
#690000
b11 3
#700000
0(
#725000
1A
b0 '
b0 6
b0 ;
b0 B
b0 T
0C
b0 Q
xN
b0 R
b0 D
b0 O
b0 K
b0 y
b0 J
b0 V
b0 H
b0 F
b0 L
b0 z
b10000 !
b10000 "
b10000 9
b10000 G
b0 %
b0 5
b0 =
b0 ?
b0 X
b11111111111111110000000100000001 s
b0 #
b0 8
b0 >
b0 :
b100 &
b100 4
b100 <
b100 7
1(
#740000
b100 3
b1 0
#750000
0(
#775000
0A
b10000 '
b10000 6
b10000 ;
b10000 B
b10000 T
b11111111111111111111111111110000 Q
0N
b10000 R
1$
0M
b1 K
b1 y
b10000 D
b10000 O
b10000 F
b101011 H
b100011010101111001101 %
b100011010101111001101 5
b100011010101111001101 =
b100011010101111001101 ?
b100011010101111001101 X
b1 J
b1 V
b10100 !
b10100 "
b10100 9
b10100 G
b100011010101111001101 &
b100011010101111001101 4
b100011010101111001101 <
b100011010101111001101 7
b10101100000000010000000000010000 #
b10101100000000010000000000010000 8
b10101100000000010000000000010000 >
b10101100000000010000000000010000 :
1(
#790000
b101 3
b0 0
#800000
0(
#825000
1A
b0 '
b0 6
b0 ;
b0 B
b0 T
1M
0$
b0 L
b0 z
0C
b0 Q
xN
b0 R
b0 D
b0 O
b0 K
b0 y
b0 %
b0 5
b0 =
b0 ?
b0 X
b0 J
b0 V
b0 H
b0 F
b11000 !
b11000 "
b11000 9
b11000 G
b0 #
b0 8
b0 >
b0 :
b0 &
b0 4
b0 <
b0 7
1(
#840000
b110 3
b1 0
#850000
0(
#875000
0A
b11111111111111110000000100001001 '
b11111111111111110000000100001001 6
b11111111111111110000000100001001 ;
b11111111111111110000000100001001 B
b11111111111111110000000100001001 T
1$
0M
b10 K
b10 y
b1000 D
b1000 O
xC
b11111111111111110000000011111001 Q
b11111111111111110000000100001001 R
b1000 F
b101011 H
b100011010101111001101 %
b100011010101111001101 5
b100011010101111001101 =
b100011010101111001101 ?
b100011010101111001101 X
b10 J
b10 V
b11111111111111110000000100000001 @
b11111111111111110000000100000001 S
b11111111111111110000000100000001 W
b11 I
b11 U
b11100 !
b11100 "
b11100 9
b11100 G
b100011010101111001101 &
b100011010101111001101 4
b100011010101111001101 <
b100011010101111001101 7
b10101100011000100000000000001000 #
b10101100011000100000000000001000 8
b10101100011000100000000000001000 >
b10101100011000100000000000001000 :
1(
#890000
b111 3
b0 0
#900000
0(
#925000
b10100 '
b10100 6
b10100 ;
b10100 B
b10100 T
1M
0$
bx L
bx z
0C
b11111111111111111111111111101100 Q
0N
b10100 R
b10100 D
b10100 O
b100 K
b100 y
b0 @
b0 S
b0 W
b0 I
b0 U
b0 %
b0 5
b0 =
b0 ?
b0 X
b100 J
b100 V
b100011 H
b10100 F
b100000 !
b100000 "
b100000 9
b100000 G
b10001100000001000000000000010100 #
b10001100000001000000000000010100 8
b10001100000001000000000000010100 >
b10001100000001000000000000010100 :
bx &
bx 4
bx <
bx 7
1(
#940000
b1000 3
#950000
0(
#975000
b1000110101011110011010 '
b1000110101011110011010 6
b1000110101011110011010 ;
b1000110101011110011010 B
b1000110101011110011010 T
0C
b0 Q
xN
b1000110101011110011010 R
b1000110101011110011010 L
b1000110101011110011010 z
b100011010101111001101 D
b100011010101111001101 O
b101 K
b101 y
b100000 F
b0 H
b1 J
b1 V
b100011010101111001101 @
b100011010101111001101 S
b100011010101111001101 W
b1 I
b1 U
b100011010101111001101 %
b100011010101111001101 5
b100011010101111001101 =
b100011010101111001101 ?
b100011010101111001101 X
bx t
b100100 !
b100100 "
b100100 9
b100100 G
b100000 &
b100000 4
b100000 <
b100000 7
b1000010010100000100000 #
b1000010010100000100000 8
b1000010010100000100000 >
b1000010010100000100000 :
1(
#990000
b1001 3
#1000000
0(
#1025000
b110 K
b110 y
b10 I
b10 U
b10 J
b10 V
b101000 !
b101000 "
b101000 9
b101000 G
b1000110101011110011010 u
b10000100011000000100000 #
b10000100011000000100000 8
b10000100011000000100000 >
b10000100011000000100000 :
bx &
bx 4
bx <
bx 7
1(
#1040000
b1010 3
#1050000
0(
#1075000
b111 K
b111 y
b1 I
b1 U
b1000110101011110011010 v
b101100 !
b101100 "
b101100 9
b101100 G
b1000100011100000100000 #
b1000100011100000100000 8
b1000100011100000100000 >
b1000100011100000100000 :
1(
#1090000
b1011 3
#1100000
0(
#1125000
b1000 K
b1000 y
b10 I
b10 U
b1 J
b1 V
b110000 !
b110000 "
b110000 9
b110000 G
b1000110101011110011010 w
b10000010100000000100000 #
b10000010100000000100000 8
b10000010100000000100000 >
b10000010100000000100000 :
1(
#1140000
b1100 3
#1150000
0(
#1175000
xA
bx '
bx 6
bx ;
bx B
bx T
0M
1$
b11111111111111111111111111111000 D
b11111111111111111111111111111000 O
xC
bx Q
bx R
b11 K
b11 y
b111000 F
b101011 H
b11111111111111110000000100000001 %
b11111111111111110000000100000001 5
b11111111111111110000000100000001 =
b11111111111111110000000100000001 ?
b11111111111111110000000100000001 X
b11 J
b11 V
bx @
bx S
bx W
b100 I
b100 U
b1000110101011110011010 x
b110100 !
b110100 "
b110100 9
b110100 G
b10101100100000111111111111111000 #
b10101100100000111111111111111000 8
b10101100100000111111111111111000 >
b10101100100000111111111111111000 :
1(
#1190000
b1101 3
#1200000
0(
#1225000
0A
b11100 '
b11100 6
b11100 ;
b11100 B
b11100 T
0C
b11111111111111111111111111100100 Q
0N
b11100 R
b11100 D
b11100 O
b101 K
b101 y
b0 @
b0 S
b0 W
b0 I
b0 U
b1000110101011110011010 %
b1000110101011110011010 5
b1000110101011110011010 =
b1000110101011110011010 ?
b1000110101011110011010 X
b101 J
b101 V
b11100 F
b111000 !
b111000 "
b111000 9
b111000 G
b10101100000001010000000000011100 #
b10101100000001010000000000011100 8
b10101100000001010000000000011100 >
b10101100000001010000000000011100 :
1(
#1240000
b1110 3
#1250000
0(
#1275000
b100000 '
b100000 6
b100000 ;
b100000 B
b100000 T
b11111111111111111111111111100000 Q
b100000 R
b100000 D
b100000 O
b110 K
b110 y
b100000 F
b110 J
b110 V
b111100 !
b111100 "
b111100 9
b111100 G
b0 &
b0 4
b0 <
b0 7
b10101100000001100000000000100000 #
b10101100000001100000000000100000 8
b10101100000001100000000000100000 >
b10101100000001100000000000100000 :
1(
#1290000
b1111 3
#1300000
0(
#1325000
b100100 '
b100100 6
b100100 ;
b100100 B
b100100 T
b11111111111111111111111111011100 Q
b100100 R
b100100 D
b100100 O
b111 K
b111 y
b111 J
b111 V
b100100 F
b1000000 !
b1000000 "
b1000000 9
b1000000 G
b10101100000001110000000000100100 #
b10101100000001110000000000100100 8
b10101100000001110000000000100100 >
b10101100000001110000000000100100 :
1(
#1340000
b10000 3
#1350000
0(
#1375000
b101000 '
b101000 6
b101000 ;
b101000 B
b101000 T
b11111111111111111111111111011000 Q
b101000 R
b101000 D
b101000 O
b1000 K
b1000 y
b101000 F
b1000 J
b1000 V
b1000100 !
b1000100 "
b1000100 9
b1000100 G
b10101100000010000000000000101000 #
b10101100000010000000000000101000 8
b10101100000010000000000000101000 >
b10101100000010000000000000101000 :
1(
#1390000
b10001 3
#1400000
0(
#1425000
1A
b0 '
b0 6
b0 ;
b0 B
b0 T
0$
1M
b0 L
b0 z
b1 E
b1 P
0C
b0 Q
xN
b1000110101011110011010 R
b100011010101111001101 D
b100011010101111001101 O
b101 K
b101 y
b100011010101111001101 @
b100011010101111001101 S
b100011010101111001101 W
b1 I
b1 U
b100011010101111001101 %
b100011010101111001101 5
b100011010101111001101 =
b100011010101111001101 ?
b100011010101111001101 X
b1 J
b1 V
b0 H
b100010 F
b1001000 !
b1001000 "
b1001000 9
b1001000 G
b1000010010100000100010 #
b1000010010100000100010 8
b1000010010100000100010 >
b1000010010100000100010 :
1(
#1440000
b10010 3
#1450000
0(
#1475000
b110 K
b110 y
b10 J
b10 V
b10 I
b10 U
b0 u
b1001100 !
b1001100 "
b1001100 9
b1001100 G
b100011010101111001101 &
b100011010101111001101 4
b100011010101111001101 <
b100011010101111001101 7
b10000100011000000100010 #
b10000100011000000100010 8
b10000100011000000100010 >
b10000100011000000100010 :
1(
#1490000
b10011 3
#1500000
0(
#1525000
b111 K
b111 y
b1 I
b1 U
b1010000 !
b1010000 "
b1010000 9
b1010000 G
b0 v
b1000100011100000100010 #
b1000100011100000100010 8
b1000100011100000100010 >
b1000100011100000100010 :
1(
#1540000
b10100 3
#1550000
0(
#1575000
b1000 K
b1000 y
b1 J
b1 V
b10 I
b10 U
b0 w
b1010100 !
b1010100 "
b1010100 9
b1010100 G
b10000010100000000100010 #
b10000010100000000100010 8
b10000010100000000100010 >
b10000010100000000100010 :
1(
#1590000
b10101 3
#1600000
0(
